{"cameraMode":{"drawMode":0,"name":"Shaded","section":"Shading Mode"},"sceneLighting":true,"audioPlay":false,"sceneViewState":{"showFog":true,"showMaterialUpdate":false,"showSkybox":true,"showFlares":true,"showImageEffects":true,"showParticleSystems":true},"in2DMode":false,"pivot":{"x":-20.716875076293947,"y":0.9989968538284302,"z":1.481863021850586},"rotation":{"x":-0.07279052585363388,"y":0.8947231769561768,"z":-0.411216139793396,"w":-0.15837833285331727},"size":15.622316360473633,"orthographic":false}